8db75255b6e19b26f7a3__mypyc.cpython-311-x86_64-linux-musl.so
compiled-0.3.0.dist-info/METADATA
compiled-0.3.0.dist-info/RECORD
compiled-0.3.0.dist-info/top_level.txt
compiled-0.3.0.dist-info/WHEEL
compiled-0.3.0.dist-info/entry_points.txt
compiled/difflib.cpython-311-x86_64-linux-musl.so
compiled/difflib.py
compiled/__init__.py
compiled/tomllib/_types.cpython-311-x86_64-linux-musl.so
compiled/tomllib/_types.py
compiled/tomllib/_parser.py
compiled/tomllib/_re.cpython-311-x86_64-linux-musl.so
compiled/tomllib/_re.py
compiled/tomllib/_parser.cpython-311-x86_64-linux-musl.so
compiled/tomllib/__init__.py
compiled/tomllib/__init__.cpython-311-x86_64-linux-musl.so
