Metadata-Version: 2.1
Name: compiled
Version: 0.3.0
Summary: Compiled versions of the Python standard library.
Author-email: Tushar Sadhwani <tushar.sadhwani000@gmail.com>
License: PSF license
Project-URL: Homepage, https://github.com/tusharsadhwani/compiled
Classifier: Operating System :: Microsoft :: Windows
Classifier: Operating System :: MacOS
Classifier: Operating System :: POSIX :: Linux
Classifier: Programming Language :: Python :: 3.8
Classifier: Programming Language :: Python :: 3.9
Classifier: Programming Language :: Python :: 3.10
Classifier: Programming Language :: Python :: 3.11
Classifier: Programming Language :: Python :: 3.12
Classifier: Typing :: Typed
Requires-Python: >=3.11
